ukrdc_sqla/__init__.py
ukrdc_sqla/empi.py
ukrdc_sqla/errorsdb.py
ukrdc_sqla/pkb.py
ukrdc_sqla/py.typed
ukrdc_sqla/repository.py
ukrdc_sqla/stats.py
ukrdc_sqla/ukrdc.py
ukrdc_sqla/utils/__init__.py
ukrdc_sqla/utils/extras.py
ukrdc_sqla/utils/links.py
ukrdc_sqla/xmlarchive.py
ukrdc_sqla-3.0.3.dist-info/METADATA
ukrdc_sqla-3.0.3.dist-info/WHEEL
ukrdc_sqla-3.0.3.dist-info/licenses/LICENSE
ukrdc_sqla-3.0.3.dist-info/RECORD
