Metadata-Version: 2.4
Name: ukrdc-sqla
Version: 3.0.3
Summary: SQLAlchemy models for the UKRDC
License-File: LICENSE
Author: Joel Collins
Author-email: joel.collins@renalregistry.nhs.uk
Requires-Python: >=3.8.0,<4.0
Classifier: Programming Language :: Python :: 3
Classifier: Programming Language :: Python :: 3.8
Classifier: Programming Language :: Python :: 3.9
Classifier: Programming Language :: Python :: 3.10
Classifier: Programming Language :: Python :: 3.11
Classifier: Programming Language :: Python :: 3.12
Classifier: Programming Language :: Python :: 3.13
Classifier: Programming Language :: Python :: 3.14
Requires-Dist: SQLAlchemy (>=1.4.25,<3.0.0)
